gettestmail/__init__.py
gettestmail/client.py
gettestmail/models.py
gettestmail-1.0.1.dist-info/LICENSE
gettestmail-1.0.1.dist-info/METADATA
gettestmail-1.0.1.dist-info/WHEEL
gettestmail-1.0.1.dist-info/top_level.txt
gettestmail-1.0.1.dist-info/RECORD
