Metadata-Version: 2.1
Name: gettestmail
Version: 1.0.1
Summary: A Python client library for the GetTestMail API
Home-page: https://github.com/gettestmail/python-sdk
Author: Bobby Donchev
Author-email: support@gettestmail.com
Classifier: Development Status :: 3 - Alpha
Classifier: Intended Audience :: Developers
Classifier: License :: OSI Approved :: MIT License
Classifier: Operating System :: OS Independent
Classifier: Programming Language :: Python :: 3
Classifier: Programming Language :: Python :: 3.6
Classifier: Programming Language :: Python :: 3.7
Classifier: Programming Language :: Python :: 3.8
Classifier: Programming Language :: Python :: 3.9
Requires-Python: >=3.6
License-File: LICENSE
Requires-Dist: requests
